{
  "contact": [
    {
      "title": "Engineer",
      "name": "Yılmaz Karaagac",
      "email": "y.karaagac@gmail.com",
      "phonenumber": "5554466688",
      "country_code": "TR",
      "text": "asdasdasdas",
      "id": 1
    },
    {
      "title": "Mechanical Engineer",
      "name": "Soner Bedir",
      "email": "s.bedir@gmail.com",
      "phonenumber": "55446688",
      "country_code": "TR",
      "text": "asfshfgkıgfngdfhb",
      "id": 2
    },
    {
      "title": "sdasd",
      "name": "asdasd",
      "email": "sadfsdf",
      "phonenumber": "asdfasdf",
      "country_code": "KE",
      "text": "sdfsdf",
      "id": 3
    },
    {
      "title": "asd",
      "name": "asd",
      "email": "asd",
      "phonenumber": "asd",
      "country_code": "BR",
      "text": "asffsaafs",
      "id": 4
    },
    {
      "title": "werwer",
      "name": "werwer",
      "email": "werwer",
      "phonenumber": "werwer",
      "country_code": "BR",
      "text": "f3",
      "id": 5
    },
    {
      "title": "fdwgg",
      "name": "grerg",
      "email": "grerg",
      "phonenumber": "rgg",
      "country_code": "KE",
      "text": "ergerg",
      "id": 6
    },
    {
      "title": "",
      "name": "",
      "email": "",
      "phonenumber": "",
      "countryName": "",
      "text": "sdfghj",
      "id": 7
    },
    {
      "title": "Engineer",
      "name": "Soner Bedir",
      "email": "sonerbedir1@gmail.com",
      "phonenumber": "5555445558",
      "countryName": "Turkey",
      "text": "sdfsddsfsdfdsfsd",
      "id": 8
    }
  ]
}